xai_metrics/__init__.py
xai_metrics/examine_explanation.py
xai_metrics-0.0.2.dist-info/LICENSE
xai_metrics-0.0.2.dist-info/METADATA
xai_metrics-0.0.2.dist-info/WHEEL
xai_metrics-0.0.2.dist-info/top_level.txt
xai_metrics-0.0.2.dist-info/RECORD
