Metadata-Version: 2.1
Name: xai-metrics
Version: 0.0.2
Summary: A package for analysis and evaluating metrics for Explainable AI (XAI)
Home-page: https://github.com/greghvk/ml_models_explainability
Author: Grzegorz Huk
Author-email: mrgreg557@gmail.com
License: MIT
Keywords: xai,explainability,ai,machine learning
Platform: UNKNOWN
Classifier: Development Status :: 3 - Alpha
Classifier: Programming Language :: Python :: 3
Classifier: License :: OSI Approved :: MIT License
Classifier: Operating System :: OS Independent
Requires-Python: >=3
Requires-Dist: lime (>=0.1)
Requires-Dist: matplotlib (>=3.1)
Requires-Dist: numpy (>=1.18)
Requires-Dist: pandas (>=1.0)
Requires-Dist: seaborn (>=0.10)
Requires-Dist: shap (>=0.34)
Requires-Dist: scikit-learn (>=0.22)
